app_asset_translator/ConfigUtil.py
app_asset_translator/Constants.py
app_asset_translator/GenerateCsvFromResources.py
app_asset_translator/GenerateResourcesFromCsv.py
app_asset_translator/LanguageUtil.py
app_asset_translator/__init__.py
app_asset_translator/translator_scripts.py
app_asset_translator-0.3.2.dist-info/licenses/LICENSE.txt
app_asset_translator-0.3.2.dist-info/METADATA
app_asset_translator-0.3.2.dist-info/WHEEL
app_asset_translator-0.3.2.dist-info/entry_points.txt
app_asset_translator-0.3.2.dist-info/top_level.txt
app_asset_translator-0.3.2.dist-info/RECORD
