Metadata-Version: 2.4
Name: app_asset_translator
Version: 0.3.2
Summary: Small tool to generate translations files to csv and back
Home-page: https://github.com/StellaAlexis/AppAssetTranslator
Download-URL: https://github.com/StellaAlexis/AppAssetTranslator
Author: Originally by Myler Media, Currently maintained by Stella Schalkwijk
License: GNU GPLv3
Project-URL: Homepage, https://github.com/StellaAlexis/AppAssetTranslator
Project-URL: Download, https://github.com/StellaAlexis/AppAssetTranslator
Requires-Python: >=3.6
License-File: LICENSE.txt
Requires-Dist: pandas
Requires-Dist: PyYAML
Dynamic: download-url
Dynamic: home-page
Dynamic: license-file
